cynia_agents/__init__.py
cynia_agents/artifact_manager.py
cynia_agents/component_base.py
cynia_agents/component_load_guard.py
cynia_agents/component_manager.py
cynia_agents/components.json
cynia_agents/config.py
cynia_agents/cynia_cli.py
cynia_agents/dev_log2.txt
cynia_agents/dev_log3.txt
cynia_agents/dev_log4.txt
cynia_agents/log_writer.py
cynia_agents/prompts.json
cynia_agents/ui_components.py
cynia_agents/utils.py
cynia_agents/version_checker.py
cynia_agents/web.py
cynia_agents/__pycache__/__init__.cpython-39.pyc
cynia_agents/__pycache__/artifact_manager.cpython-39.pyc
cynia_agents/__pycache__/component_base.cpython-39.pyc
cynia_agents/__pycache__/component_load_guard.cpython-39.pyc
cynia_agents/__pycache__/component_manager.cpython-39.pyc
cynia_agents/__pycache__/config.cpython-39.pyc
cynia_agents/__pycache__/cynia_cli.cpython-39.pyc
cynia_agents/__pycache__/log_writer.cpython-39.pyc
cynia_agents/__pycache__/ui_components.cpython-39.pyc
cynia_agents/__pycache__/utils.cpython-39.pyc
cynia_agents/__pycache__/version_checker.cpython-39.pyc
cynia_agents/components/__init__.py
cynia_agents/components/example_component.py
cynia_agents/components/__pycache__/__init__.cpython-312.pyc
cynia_agents/components/__pycache__/__init__.cpython-39.pyc
cynia_agents/components/__pycache__/example_component.cpython-312.pyc
cynia_agents/components/__pycache__/example_component.cpython-39.pyc
cynia_agents/components/__pycache__/example_versioned_component.cpython-39.pyc
cynia_agents/hot_reload/__init__.py
cynia_agents/hot_reload/cache.py
cynia_agents/hot_reload/dependency.py
cynia_agents/hot_reload/error_recovery.py
cynia_agents/hot_reload/errors.py
cynia_agents/hot_reload/file_watcher.py
cynia_agents/hot_reload/hot_reload_manager.py
cynia_agents/hot_reload/loader.py
cynia_agents/hot_reload/logging_system.py
cynia_agents/hot_reload/models.py
cynia_agents/hot_reload/performance.py
cynia_agents/hot_reload/resource_monitor.py
cynia_agents/hot_reload/unload_manager.py
cynia_agents-2.1.0.dist-info/licenses/LICENSE
cynia_agents-2.1.0.dist-info/METADATA
cynia_agents-2.1.0.dist-info/WHEEL
cynia_agents-2.1.0.dist-info/entry_points.txt
cynia_agents-2.1.0.dist-info/top_level.txt
cynia_agents-2.1.0.dist-info/RECORD
